{
  "version": 1,
  "seq": 7,
  "list": [
    {
      "type": "symbol",
      "owner": null,
      "seq": 1,
      "x": 306.62234982332166,
      "y": 129.21819787985865,
      "scale": 1.6,
      "rotation": 0,
      "version": 1,
      "symbol": "correct"
    },
    {
      "type": "symbol",
      "owner": null,
      "seq": 2,
      "x": 220.02782685512375,
      "y": 432.75176678445234,
      "scale": 1.6,
      "rotation": 0,
      "version": 1,
      "symbol": "correct"
    },
    {
      "type": "symbol",
      "owner": null,
      "seq": 3,
      "x": 179.88869257950546,
      "y": 757.6192579505301,
      "scale": 1.6,
      "rotation": 0,
      "version": 1,
      "symbol": "wrong"
    },
    {
      "type": "symbol",
      "owner": null,
      "seq": 4,
      "x": 877.6029151943465,
      "y": 418.08745583038876,
      "scale": 1.6,
      "rotation": 0,
      "version": 1,
      "symbol": "wrong"
    },
    {
      "type": "text",
      "owner": null,
      "seq": 5,
      "x": 448.4178445229684,
      "y": 845.7270318021202,
      "scale": 1.6,
      "rotation": 0,
      "version": 1,
      "width": 0,
      "text": "哈哈"
    },
    {
      "version": 1,
      "type": "drawing",
      "owner": null,
      "seq": 6,
      "x": 0,
      "y": 0,
      "segments": [
        {
          "points": [
            {
              "x": 735.7411660777386,
              "y": 948.2332155477033
            },
            {
              "x": 736.7460247349825,
              "y": 949.2380742049471
            },
            {
              "x": 749.809187279152,
              "y": 963.3060954063604
            },
            {
              "x": 762.8723498233217,
              "y": 974.3595406360424
            },
            {
              "x": 770.9112190812723,
              "y": 980.3886925795053
            },
            {
              "x": 774.9306537102475,
              "y": 983.4032685512369
            },
            {
              "x": 777.9452296819788,
              "y": 986.4178445229683
            },
            {
              "x": 780.9598056537104,
              "y": 993.451855123675
            },
            {
              "x": 783.9743816254418,
              "y": 1003.5004416961132
            },
            {
              "x": 786.9889575971733,
              "y": 1021.5878975265019
            },
            {
              "x": 788.9986749116608,
              "y": 1033.6462014134274
            },
            {
              "x": 790.0035335689047,
              "y": 1044.6996466431094
            },
            {
              "x": 792.0132508833924,
              "y": 1053.743374558304
            },
            {
              "x": 794.0229681978799,
              "y": 1060.7773851590105
            },
            {
              "x": 797.0375441696115,
              "y": 1066.8065371024734
            },
            {
              "x": 802.0618374558305,
              "y": 1075.8502650176679
            },
            {
              "x": 805.0764134275619,
              "y": 1082.8842756183744
            },
            {
              "x": 807.0861307420496,
              "y": 1091.928003533569
            },
            {
              "x": 807.0861307420496,
              "y": 1102.981448763251
            },
            {
              "x": 803.0225265017668,
              "y": 1121.0689045936394
            },
            {
              "x": 789.9041519434629,
              "y": 1140.5697879858658
            },
            {
              "x": 778.7292402826856,
              "y": 1162.0803886925794
            },
            {
              "x": 770.6020318021203,
              "y": 1174.1386925795052
            },
            {
              "x": 763.4907243816256,
              "y": 1183.1824204946995
            },
            {
              "x": 760.4430212014136,
              "y": 1187.201855123675
            },
            {
              "x": 758.4112190812723,
              "y": 1190.2164310954063
            },
            {
              "x": 757.3953180212015,
              "y": 1191.2212897526501
            },
            {
              "x": 756.3794169611308,
              "y": 1191.2212897526501
            },
            {
              "x": 750.2840106007068,
              "y": 1187.1576855123674
            },
            {
              "x": 738.0931978798587,
              "y": 1182.078180212014
            },
            {
              "x": 722.8546819787987,
              "y": 1174.9668727915193
            },
            {
              "x": 707.6382508833924,
              "y": 1166.850706713781
            },
            {
              "x": 696.4633392226149,
              "y": 1159.7393992932862
            },
            {
              "x": 690.3679328621909,
              "y": 1152.6280918727914
            },
            {
              "x": 686.3043286219083,
              "y": 1145.5167844522969
            },
            {
              "x": 681.2248233215548,
              "y": 1139.4213780918728
            },
            {
              "x": 678.1771201413428,
              "y": 1131.2941696113073
            },
            {
              "x": 674.1135159010603,
              "y": 1122.1510600706713
            },
            {
              "x": 668.0181095406363,
              "y": 1107.9615724381624
            },
            {
              "x": 659.9019434628976,
              "y": 1090.7354240282684
            },
            {
              "x": 651.7747349823323,
              "y": 1075.5189929328621
            },
            {
              "x": 648.7270318021203,
              "y": 1064.3440812720848
            },
            {
              "x": 646.6952296819788,
              "y": 1054.196113074205
            },
            {
              "x": 644.6634275618376,
              "y": 1040.9893992932862
            },
            {
              "x": 643.6475265017668,
              "y": 1024.7460247349823
            },
            {
              "x": 643.6475265017668,
              "y": 1007.4867491166079
            },
            {
              "x": 646.6621024734984,
              "y": 995.2959363957597
            },
            {
              "x": 649.6766784452298,
              "y": 987.1687279151944
            },
            {
              "x": 653.696113074205,
              "y": 980.0574204946996
            },
            {
              "x": 655.7058303886927,
              "y": 975.9938162544171
            },
            {
              "x": 658.7204063604242,
              "y": 972.9461130742051
            },
            {
              "x": 659.7252650176679,
              "y": 970.9143109540636
            },
            {
              "x": 663.7446996466433,
              "y": 967.8666077738516
            },
            {
              "x": 671.7835689045937,
              "y": 961.7712014134275
            },
            {
              "x": 683.8418727915196,
              "y": 955.6757950530035
            },
            {
              "x": 691.88074204947,
              "y": 951.612190812721
            },
            {
              "x": 695.9001766784454,
              "y": 948.564487632509
            },
            {
              "x": 697.9098939929329,
              "y": 947.5485865724382
            },
            {
              "x": 699.9196113074206,
              "y": 947.5485865724382
            },
            {
              "x": 702.934187279152,
              "y": 947.5485865724382
            },
            {
              "x": 708.9633392226149,
              "y": 946.5326855123675
            },
            {
              "x": 713.9876325088339,
              "y": 946.5326855123675
            },
            {
              "x": 720.0167844522969,
              "y": 946.5326855123675
            },
            {
              "x": 724.0362190812723,
              "y": 946.5326855123675
            },
            {
              "x": 725.0410777385159,
              "y": 946.5326855123675
            },
            {
              "x": 726.0459363957598,
              "y": 947.5375441696114
            },
            {
              "x": 728.0556537102475,
              "y": 947.5375441696114
            },
            {
              "x": 729.0605123674914,
              "y": 948.5424028268552
            }
          ],
          "lineWidth": 3.2
        },
        {
          "points": [
            {
              "x": 631.4125441696115,
              "y": 1092.1267667844522
            },
            {
              "x": 632.4174028268553,
              "y": 1092.1267667844522
            },
            {
              "x": 638.4465547703182,
              "y": 1094.13648409894
            },
            {
              "x": 653.5194346289754,
              "y": 1095.1413427561838
            },
            {
              "x": 675.6263250883394,
              "y": 1095.1413427561838
            },
            {
              "x": 693.7137809187279,
              "y": 1092.0936395759718
            },
            {
              "x": 708.7866607773854,
              "y": 1088.030035335689
            },
            {
              "x": 718.8352473498235,
              "y": 1085.9982332155475
            },
            {
              "x": 722.8546819787987,
              "y": 1084.982332155477
            },
            {
              "x": 722.8546819787987,
              "y": 1083.9664310954063
            },
            {
              "x": 723.8595406360425,
              "y": 1083.9664310954063
            },
            {
              "x": 724.8643992932864,
              "y": 1083.9664310954063
            },
            {
              "x": 729.8886925795055,
              "y": 1082.9505300353355
            },
            {
              "x": 734.9129858657245,
              "y": 1081.934628975265
            },
            {
              "x": 735.9178445229684,
              "y": 1081.934628975265
            },
            {
              "x": 737.9275618374559,
              "y": 1081.934628975265
            },
            {
              "x": 741.9469964664313,
              "y": 1081.934628975265
            },
            {
              "x": 746.9712897526504,
              "y": 1079.9028268551235
            },
            {
              "x": 751.9955830388694,
              "y": 1078.886925795053
            },
            {
              "x": 760.0344522968198,
              "y": 1075.839222614841
            },
            {
              "x": 768.0733215547705,
              "y": 1072.791519434629
            },
            {
              "x": 775.1073321554773,
              "y": 1069.743816254417
            },
            {
              "x": 779.1267667844525,
              "y": 1068.7279151943462
            },
            {
              "x": 780.1316254416963,
              "y": 1068.7279151943462
            },
            {
              "x": 783.1462014134277,
              "y": 1066.696113074205
            },
            {
              "x": 788.1704946996467,
              "y": 1063.648409893993
            },
            {
              "x": 793.1947879858658,
              "y": 1060.600706713781
            },
            {
              "x": 799.2239399293287,
              "y": 1058.5689045936394
            },
            {
              "x": 805.2530918727916,
              "y": 1055.5212014134274
            },
            {
              "x": 813.2919611307423,
              "y": 1053.4893992932862
            },
            {
              "x": 824.3454063604242,
              "y": 1050.4416961130742
            },
            {
              "x": 833.3891342756185,
              "y": 1046.3780918727914
            },
            {
              "x": 840.4231448763253,
              "y": 1045.3621908127209
            },
            {
              "x": 842.4328621908128,
              "y": 1044.3462897526501
            },
            {
              "x": 845.4474381625444,
              "y": 1043.3303886925794
            },
            {
              "x": 845.4474381625444,
              "y": 1041.2985865724381
            },
            {
              "x": 846.4522968197882,
              "y": 1040.2826855123674
            },
            {
              "x": 846.4522968197882,
              "y": 1039.2667844522969
            },
            {
              "x": 847.4571554770318,
              "y": 1039.2667844522969
            }
          ],
          "lineWidth": 3.2
        },
        {
          "points": [
            {
              "x": 768.0843639575974,
              "y": 920.362190812721
            },
            {
              "x": 768.0843639575974,
              "y": 921.3670494699646
            },
            {
              "x": 768.0843639575974,
              "y": 925.3864840989401
            },
            {
              "x": 764.0207597173146,
              "y": 936.439929328622
            },
            {
              "x": 753.8727915194347,
              "y": 954.5273851590106
            },
            {
              "x": 741.6819787985867,
              "y": 975.6294169611309
            },
            {
              "x": 728.4752650176679,
              "y": 992.7120141342756
            },
            {
              "x": 715.2685512367493,
              "y": 1007.784893992933
            },
            {
              "x": 704.0936395759718,
              "y": 1018.838339222615
            },
            {
              "x": 692.9297703180214,
              "y": 1029.8917844522969
            },
            {
              "x": 680.7500000000002,
              "y": 1045.969522968198
            },
            {
              "x": 666.5384275618376,
              "y": 1066.0666961130742
            },
            {
              "x": 655.3635159010603,
              "y": 1082.1444346289752
            },
            {
              "x": 649.2681095406363,
              "y": 1090.1833038869258
            },
            {
              "x": 647.2363074204948,
              "y": 1095.207597173145
            },
            {
              "x": 646.2204063604242,
              "y": 1095.207597173145
            },
            {
              "x": 646.2204063604242,
              "y": 1096.2124558303885
            },
            {
              "x": 646.2204063604242,
              "y": 1099.22703180212
            },
            {
              "x": 646.2204063604242,
              "y": 1101.2367491166078
            },
            {
              "x": 645.2045053003535,
              "y": 1102.2416077738515
            },
            {
              "x": 644.1886042402828,
              "y": 1103.2464664310953
            },
            {
              "x": 642.1568021201415,
              "y": 1108.2707597173144
            },
            {
              "x": 640.1250000000002,
              "y": 1111.285335689046
            },
            {
              "x": 639.1090989399295,
              "y": 1114.2999116607773
            },
            {
              "x": 637.077296819788,
              "y": 1117.3144876325089
            },
            {
              "x": 635.0454946996467,
              "y": 1121.333922261484
            },
            {
              "x": 631.9977915194347,
              "y": 1125.3533568904593
            },
            {
              "x": 630.981890459364,
              "y": 1127.363074204947
            },
            {
              "x": 628.9500883392227,
              "y": 1130.3776501766783
            },
            {
              "x": 626.9182862190814,
              "y": 1131.3825088339222
            },
            {
              "x": 624.88648409894,
              "y": 1136.4068021201413
            },
            {
              "x": 619.8069787985867,
              "y": 1142.4359540636042
            },
            {
              "x": 617.7751766784454,
              "y": 1145.4505300353355
            }
          ],
          "lineWidth": 3.2
        }
      ]
    }
  ]
}